{
    "summary": "This precompiled header file includes UIKit, Foundation frameworks and custom libraries for an iOS app, defines macros related to application and UI elements with efficient debugging capabilities.",
    "details": [
        {
            "comment": "This code is a precompiled header file, including various UIKit and Foundation frameworks, as well as custom libraries for an iOS app. It defines some global macros related to the application and UI elements.",
            "location": "\"/media/root/Prima/works/he4o/docs/src/SMG_NothingIsAll/Demo/SMGPrefixHeader.pch\":0-42",
            "content": "//\n//  SMGPrefixHeader.pch\n//  SMG_NothingIsAll\n//\n//  Created by \u8d3e  on 2017/5/3.\n//  Copyright \u00a9 2017\u5e74 XiaoGang. All rights reserved.\n//\n#import <Availability.h>\n#ifdef __OBJC__\n#import <UIKit/UIKit.h>\n#import <Foundation/Foundation.h>\n#import \"AppDelegate.h\"\n#import <CoreText/CoreText.h>\n#import \"Foundation+Log.m\"\n#import \"UIView+Extension.h\"\n#import \"UIColor+expanded.h\"\n#import \"AIHeader.h\"\n#import \"HEView.h\"\n#import \"NSLog+Extension.h\"\n#import \"AITest.h\"\n#import \"RLTrainer.h\"\n#import \"XGDebug.h\"\n#import \"XGDebugModel.h\"\n#import \"TCDebug.h\"\n#import \"XGConfig.h\"\n#endif\n//MARK:===============================================================\n//MARK:                     < \u5168\u5c40\u5b8f/Demo\u5b8f >\n//MARK:===============================================================\n/**\n *  MARK:--------------------application--------------------\n */\n#define theApp ((AppDelegate*)[[UIApplication sharedApplication] delegate])\n#define isSimulator TARGET_OS_SIMULATOR\n/**\n *  MARK:--------------------ui--------------------\n */\n#define ScreenHeight [[UIScreen mainScreen] bounds].size.height"
        },
        {
            "comment": "This code defines various color and logging macros for an iOS app. The color macros use RGB, RGBA, Hex, and HSB to define and create UIColor objects. The logging macro, TPLog, allows for formatted log messages with optional parameters. TheApp, nvView, tv, and rlTrainer are used in the logging macro.",
            "location": "\"/media/root/Prima/works/he4o/docs/src/SMG_NothingIsAll/Demo/SMGPrefixHeader.pch\":43-64",
            "content": "#define ScreenWidth [[UIScreen mainScreen] bounds].size.width\n#define StateBarHeight 20\n/**\n *  MARK:--------------------color--------------------\n */\n//RGB & RGBA\n#define UIColorWithRGB(R, G, B) [UIColor colorWithRed:(R)/255.0 green:(G)/255.0 blue:(B)/255.0 alpha:1]\n#define UIColorWithRGBA(R, G, B, A) [UIColor colorWithRed:(R)/255.0 green:(G)/255.0 blue:(B)/255.0 alpha:A]\n//Hex & HexA\n#define UIColorWithRGBHex(RGB_Hex) UIColorWithRGB((float)((RGB_Hex&0xFF0000)>>16), (float)((RGB_Hex&0xFF00)>>8), (float)(RGB_Hex&0xFF))\n#define UIColorWithRGBHexA(RGB_Hex,A) UIColorWithRGBA((float)((RGB_Hex&0xFF0000)>>16), (float)((RGB_Hex&0xFF00)>>8), (float)(RGB_Hex&0xFF),A)\n//HSB (\u8272\u76f8,\u9971\u5408\u5ea6,\u4eae\u5ea6)\n#define UIColorWithHSB(H, S, B) [UIColor colorWithHue:(H)/255.0 saturation:(S)/255.0 brightness:(B)/255.0 alpha:1]\n/**\n *  MARK:--------------------log--------------------\n */\n#define TPLog(a,...) [theApp setTipLog:STRFORMAT(a,##__VA_ARGS__)]\n#define theNV (theApp.nvView)\n#define theTV (theApp.tv)\n#define theRT [RLTrainer sharedInstance]"
        },
        {
            "comment": "This code snippet defines various macros for logging and debugging purposes, such as identifying specific tags, marking different sections of the code, and interacting with the xgDebug module. The macros allow for more efficient debugging by specifying prefixes, suffixes, and file names to track the progress of the code execution.",
            "location": "\"/media/root/Prima/works/he4o/docs/src/SMG_NothingIsAll/Demo/SMGPrefixHeader.pch\":65-95",
            "content": "#define theHeLog (theApp.heLogView)\n#define theDebug [XGDebug sharedInstance]\n/**\n *  MARK:--------------------\u611f\u5b98\u7b97\u6cd5--------------------\n */\n#define visibleTag 999  //\u89c6\u89c9\u53ef\u89c1\u6807\u8bb0\n/**\n *  MARK:--------------------Identify\u6807\u8bc6 (\u5916\u56f4\u65b9)--------------------\n */\n#define EAT_RDS @\"EAT_RDS\"  //\u5438\u542e\u53cd\u5c04\u6807\u8bc6\n#define FLY_RDS @\"FLY_RDS\"  //\u6247\u7fc5\u8180\u53cd\u5c04\u6807\u8bc6 (\u7c7b\u4f3c\u6293\u63e1\u53cd\u5c04)\n#define KICK_RDS @\"KICK_RDS\"//\u811a\u8e22\u53cd\u5c04\u6807\u8bc6 (\u7c7b\u4f3c\u819d\u8df3\u53cd\u5c04)\n/**\n *  MARK:--------------------xgDebug\u8c03\u8bd5\u6a21\u5757--------------------\n *  @use \u4f7f\u7528\u65b9\u6cd5: \u6bcf\u4e2a\u6a21\u5757\u5f00\u59cb\u8c03\u7528Debug(),\u7ed3\u675f\u8c03\u7528DebugE();\n */\n#define DebugParam(p,s) [theDebug debugModuleWithPrefix:p suffix:s] //\u6307\u5b9a\u524d\u8f8d&&\u540e\u8f8d\n#define Debug() [theDebug debugModuleWithFileName:FILENAME suffix:nil]\n#define DebugS() [theDebug debugModuleWithFileName:FILENAME suffix:@\"START\"]\n#define DebugE() [theDebug debugModuleWithFileName:FILENAME suffix:@\"END\"]\n#define DebugW() [theDebug debugWrite]\n#define DebugR() [theDebug debugRead]\n#define kFILENAME FILENAME\n#define kLINE __LINE__\n/**\n *  MARK:--------------------xgDebug\u8c03\u8bd5\u4ee3\u7801\u5757--------------------\n *  @\u6ce8\u610f\u4e8b\u9879: \u4e3a\u6027\u80fd\u597d,\u8c03\u7528AddDebugCodeBlock\u540e\u5fc5\u987b\u8c03\u7528PrintDebugCodeBlock(),\u4e0d\u7136\u5b83\u4f1a\u4e00\u76f4\u7d2f\u8ba1models\u76f4\u81f3\u7cfb\u7edf\u53d8\u5361;"
        },
        {
            "comment": "This code provides a way to add and print debug code blocks with custom prefixes, making it easier to identify the source of debug information in a multi-class work environment. It uses the TCDebugPrefixV2 function to generate the prefix based on the file name or a provided key, along with a loop ID for identification purposes. The PrintDebugCodeBlock_Key and AddDebugCodeBlock_Key macros allow easy integration into code blocks for debugging purposes.",
            "location": "\"/media/root/Prima/works/he4o/docs/src/SMG_NothingIsAll/Demo/SMGPrefixHeader.pch\":96-110",
            "content": " *  @use \u4f7f\u7528\u65b9\u6cd5:\n *              1. \u5148\u5728\u4ee3\u7801\u5757\u4e4b\u95f4\u8c03\u7528AddDebugCodeBlock(\"\u81ea\u5b9a\u4e49\u540e\u8f8d\");\n *              2. \u5728\u672b\u5c3e\u8c03\u7528PrintDebugCodeBlock()\u5c06\u7ed3\u679c\u65e5\u5fd7\u6253\u51fa;\n *  @desc \u524d\u8f8d\u8bf4\u660e: \u4f7f\u7528\u5f53\u524d\u6587\u4ef6\u540d+\u5faa\u73afid;\n */\n//\u542b\u81ea\u5b9a\u4e49\u524d\u8f8d\u7248\u672c (\u9002\u7528\u4e8e\u591a\u7c7b\u5de5\u4f5c\u65f6,\u6839\u636e\u81ea\u5b9a\u4e49\u524d\u8f8d\u8de8\u7c7b\u5de5\u4f5c);\n#define AddDebugCodeBlock_Key(key,codeBlockName) [theDebug debugModuleWithPrefix:TCDebugPrefixV2(key) suffix:codeBlockName]\n#define PrintDebugCodeBlock_Key(key) [theDebug print:TCDebugPrefixV2(key) rmPrefix:TCDebugRMPrefixV2(key)]\n/**\n *  MARK:--------------------tcDebug\u62fc\u63a5\u524d\u8f8d--------------------\n *  @param prefixKey : \u4e00\u822c\u4f20\u6587\u4ef6\u540d,\u5982\u679c\u8981\u6253\u51fa\u6240\u6709\u6a21\u5757,\u5219\u53ea\u4ec5TC\u5373\u53ef,\u5982\u679c\u8981\u6253\u6240\u6709\u6587\u4ef6,\u53ef\u4ee5\u4f20\u7a7a\u5b57\u7b26\u4e32;\n */\n#define TCDebugPrefixV2(blockKey) STRFORMAT(@\"DEBUG\u5339\u914d => \u4ee3\u7801\u5757:%@ \u5faa\u73af\u5708:%lld\",blockKey,theTC.getLoopId) //TCDebug\u7684\u524d\u8f8d=\u6587\u4ef6\u540d\u7528\u6765\u5339\u914d\u7684\u524d\u90e8\u5206+\u5faa\u73afId\n#define TCDebugRMPrefixV2(blockKey) STRFORMAT(@\"DEBUG\u5339\u914d => \u4ee3\u7801\u5757:%@\",blockKey) //\u7528\u4e8e\u5220\u9664\u6240\u6709\u7684prefixKey,\u4e0d\u9650\u5faa\u73af\u6570;"
        }
    ]
}